README.md
setup.py
slack_post/__init__.py
slack_post/slackpost.py
slack_post.egg-info/PKG-INFO
slack_post.egg-info/SOURCES.txt
slack_post.egg-info/dependency_links.txt
slack_post.egg-info/entry_points.txt
slack_post.egg-info/requires.txt
slack_post.egg-info/top_level.txt